forum_dl/__init__.py
forum_dl/__main__.py
forum_dl/exceptions.py
forum_dl/forumdl.py
forum_dl/options.py
forum_dl/session.py
forum_dl/soup.py
forum_dl/version.py
forum_dl/extractors/__init__.py
forum_dl/extractors/common.py
forum_dl/extractors/discourse.py
forum_dl/extractors/hackernews.py
forum_dl/extractors/hyperkitty.py
forum_dl/extractors/hypermail.py
forum_dl/extractors/invision.py
forum_dl/extractors/phpbb.py
forum_dl/extractors/pipermail.py
forum_dl/extractors/proboards.py
forum_dl/extractors/simplemachines.py
forum_dl/extractors/vbulletin.py
forum_dl/extractors/xenforo.py
forum_dl/writers/__init__.py
forum_dl/writers/babyl.py
forum_dl/writers/common.py
forum_dl/writers/jsonl.py
forum_dl/writers/maildir.py
forum_dl/writers/mbox.py
forum_dl/writers/mh.py
forum_dl/writers/mmdf.py
forum_dl/writers/warc.py
forum_dl-0.3.0.dist-info/LICENSE
forum_dl-0.3.0.dist-info/METADATA
forum_dl-0.3.0.dist-info/WHEEL
forum_dl-0.3.0.dist-info/entry_points.txt
forum_dl-0.3.0.dist-info/top_level.txt
forum_dl-0.3.0.dist-info/RECORD
