Metadata-Version: 2.1
Name: forum-dl
Version: 0.3.0
Summary: Scrape posts and threads from forums, news aggregators, mail archives
Author-email: Mikolaj Wielgus <wielgusmikolaj@gmail.com>
License: MIT
Project-URL: repository, https://github.com/mikwielgus/forum-dl
Classifier: Development Status :: 3 - Alpha
Classifier: License :: OSI Approved :: MIT License
Classifier: Programming Language :: Python :: 3.10
Classifier: Programming Language :: Python :: 3.11
Classifier: Topic :: System :: Archiving
Requires-Python: >=3.10.11
License-File: LICENSE
Requires-Dist: pydantic
Requires-Dist: beautifulsoup4
Requires-Dist: lxml
Requires-Dist: requests
Requires-Dist: urllib3
Requires-Dist: cchardet
Requires-Dist: tenacity
Requires-Dist: python-dateutil
Requires-Dist: html2text
Requires-Dist: warcio
Provides-Extra: test
Requires-Dist: pytest ; extra == 'test'
